pyone/__init__.pyi
pyone/acl.pyi
pyone/helpers.pyi
pyone/py.typed
pyone/server.pyi
pyone/tester.pyi
pyone/util.pyi
pyone/bindings/__init__.pyi
pyone/bindings/supbind.pyi
types_pyone-0.1.7.dist-info/LICENSE
types_pyone-0.1.7.dist-info/METADATA
types_pyone-0.1.7.dist-info/WHEEL
types_pyone-0.1.7.dist-info/top_level.txt
types_pyone-0.1.7.dist-info/RECORD
